post_2_album/__init__.py
post_2_album-0.0.4.dist-info/LICENSE
post_2_album-0.0.4.dist-info/METADATA
post_2_album-0.0.4.dist-info/WHEEL
post_2_album-0.0.4.dist-info/top_level.txt
post_2_album-0.0.4.dist-info/RECORD
