Metadata-Version: 2.1
Name: post-2-album
Version: 0.0.4
Summary: Return photo list and caption from telegram post link.
Home-page: https://github.com/gaoyunzhi/post_2_album
Author: Yunzhi Gao
Author-email: gaoyunzhi@gmail.com
License: UNKNOWN
Platform: UNKNOWN
Classifier: Programming Language :: Python :: 3
Classifier: License :: OSI Approved :: MIT License
Classifier: Operating System :: OS Independent
Requires-Python: >=3.0
Requires-Dist: webgram
Requires-Dist: telegram-util
